WolongGerenShangyeSiweiZhuanjiSuibi/README.md
WolongGerenShangyeSiweiZhuanjiSuibi/__init__.py
WolongGerenShangyeSiweiZhuanjiSuibi/__main__.py
WolongGerenShangyeSiweiZhuanjiSuibi/file.pdf
WolongGerenShangyeSiweiZhuanjiSuibi/index.html
wolong_geren_shangye_siwei_zhuanji_suibi-2022.10.15.0.dist-info/METADATA
wolong_geren_shangye_siwei_zhuanji_suibi-2022.10.15.0.dist-info/WHEEL
wolong_geren_shangye_siwei_zhuanji_suibi-2022.10.15.0.dist-info/entry_points.txt
wolong_geren_shangye_siwei_zhuanji_suibi-2022.10.15.0.dist-info/top_level.txt
wolong_geren_shangye_siwei_zhuanji_suibi-2022.10.15.0.dist-info/RECORD
